[{"name":"3310","description":"somthing longer","brand":"nokia","imageUrl":"http://localhost:3001/img/productsmr-bean.gif","price":100,"category":"smartphones","createdAt":"2022-12-23T14:36:08.513Z","_id":"5v5pvkh0lc0m87gi","reviews":[{"comment":"modified","rate":3,"createdAt":"2022-12-23T14:37:36.371Z","_id":"5v5pvkh0lc0ma38z","product_Id":"5v5pvkh0lc0m87gi"}]},{"name":"3310","description":"somthing longer","brand":"nokia","imageUrl":"https://drop.ndtv.com/TECH/product_database/images/2152017124957PM_635_nokia_3310.jpeg?downsize=*:420&output-quality=80","price":100,"category":"notsosmartphones","createdAt":"2022-12-23T16:31:59.640Z","updatedAt":"2022-12-23T16:31:59.640Z","_id":"5v5pvnj0lc0qd6zd","reviews":[]}]
